cloudsh/__init__.py
cloudsh/__main__.py
cloudsh/args/cat.toml
cloudsh/args/complete.toml
cloudsh/args/cp.toml
cloudsh/args/head.toml
cloudsh/args/less.toml
cloudsh/args/ls.toml
cloudsh/args/mkdir.toml
cloudsh/args/more.toml
cloudsh/args/mv.toml
cloudsh/args/rm.toml
cloudsh/args/sink.toml
cloudsh/args/tail.toml
cloudsh/args/touch.toml
cloudsh/commands/cat.py
cloudsh/commands/complete.py
cloudsh/commands/cp.py
cloudsh/commands/head.py
cloudsh/commands/less.py
cloudsh/commands/ls.py
cloudsh/commands/mkdir.py
cloudsh/commands/more.py
cloudsh/commands/mv.py
cloudsh/commands/rm.py
cloudsh/commands/sink.py
cloudsh/commands/tail.py
cloudsh/commands/touch.py
cloudsh/main.py
cloudsh/utils.py
cloudsh-0.3.7.dist-info/METADATA
cloudsh-0.3.7.dist-info/WHEEL
cloudsh-0.3.7.dist-info/entry_points.txt
cloudsh-0.3.7.dist-info/licenses/LICENSE
cloudsh-0.3.7.dist-info/RECORD
